kanji2arabic/__init__.py
kanji2arabic-1.1.3.dist-info/LICENSE
kanji2arabic-1.1.3.dist-info/WHEEL
kanji2arabic-1.1.3.dist-info/METADATA
kanji2arabic-1.1.3.dist-info/RECORD
