Metadata-Version: 2.1
Name: kanji2arabic
Version: 1.1.3
Summary: Convert Kanji numerals to Arabic numerals.
Home-page: https://github.com/interman-corp/kanji2arabic
License: MIT
Keywords: Japanese,kanji,int2kanji,kanji2int,convert
Author: hgs-interman
Author-email: system@interman.co.jp
Maintainer: hgs-interman
Maintainer-email: system@interman.co.jp
Requires-Python: >=3.6,<4.0
Classifier: License :: OSI Approved :: MIT License
Classifier: Programming Language :: Python :: 3
Classifier: Programming Language :: Python :: 3.6
Classifier: Programming Language :: Python :: 3.7
Classifier: Programming Language :: Python :: 3.8
Classifier: Programming Language :: Python :: 3.9
Classifier: Programming Language :: Python :: 3.10
Classifier: Programming Language :: Python :: 3.10
Classifier: Programming Language :: Python :: 3.6
Classifier: Programming Language :: Python :: 3.7
Classifier: Programming Language :: Python :: 3.8
Classifier: Programming Language :: Python :: 3.9
Requires-Dist: kanjize (==1.3.0)
Project-URL: Repository, https://github.com/interman-corp/kanji2arabic
